Prac6/design.sv
`timescale 1ns / 1ps

module reg_mem (addr, data_in, wen, clk, data_out);

    parameter DATA_WIDTH = 8; //8 bit wide data
    parameter ADDR_BITS = 5; //32 Addresses

    input [ADDR_BITS-1:0] addr;
    input [DATA_WIDTH-1:0] data_in;
    input wen;
    input clk;
    output [DATA_WIDTH-1:0] data_out;

    reg [DATA_WIDTH-1:0] data_out;

    //8 memory locations each storing a 4bits wide value
    reg [DATA_WIDTH-1:0] mem_array [(2**ADDR_BITS)-1:0];

  
    always @(posedge clk) begin

        if (wen) begin //Write
            mem_array [addr] <= data_in;
            data_out <= #(DATA_WIDTH)'b0;
        end

        else begin //Read
            data_out <= mem_array[addr];
        end
    end

endmodule

module CU (clk,rst, instr, result2, operand1, operand2, offset, opcode, sel1, sel3, w_r, r0, r1, r2, r3);
    //Defaults unless overwritten during instantiation
    parameter DATA_WIDTH = 8; //8 bit wide data
    parameter ADDR_BITS = 5; //32 Addresses
    parameter INSTR_WIDTH =20; 
    //INPUTS
    input clk,rst;
    input [INSTR_WIDTH-1:0]instr;
    input [DATA_WIDTH-1:0] result2;

    //OUTPUTS
    output reg [DATA_WIDTH-1:0] operand1;
    output reg [DATA_WIDTH-1:0] operand2;
    output reg [DATA_WIDTH-1:0] offset;
    output reg [3:0] opcode;
    output reg sel1, sel3, w_r;
  	//Output registers to monitor internal registers in EPWave
    output reg [DATA_WIDTH-1:0] r0,r1,r2,r3;
  
    //REGISTER FILE: CU internal register file of 4 registers.  This is a over simplication of a real solution
    reg [DATA_WIDTH-1:0] regfile [0:3];
    reg [INSTR_WIDTH-1:0]instruction;
    
    assign r0 = regfile[0];
    assign r1 = regfile[1];
    assign r2 = regfile[2];
    assign r3 = regfile[3];
  
    //STATES
    parameter RESET = 4'b0000;
    parameter DECODE = 4'b0001;
    parameter EXECUTE = 4'b0010;
    parameter MEM_ACCESS = 4'b0100;
    parameter WRITE_BACK = 4'b1000;
        
    reg [3:0] state = RESET;
    
    
    always @(posedge clk) begin
        instruction = instr;
        case (state)
            RESET : begin //#0
                if (instruction[19:18] == 2'b00)  begin
                    state = RESET; 
                    end else begin
                    state = DECODE; //#1
                    end
                //-----------------------------
                //Write initial values to regfile
                regfile[0]<= 8'd0;
                regfile[1]<= 8'd1;
                regfile[2]<= 8'd2;
                regfile[3]<= 8'd3;

                //Set output reset defaults
                operand1 <= #(DATA_WIDTH)'d0;
                operand2 <= #(DATA_WIDTH)'d0;
                offset <= #(DATA_WIDTH)'d0;
                opcode <= 4'b1111;
                sel1 <= 0;
                sel3 <= 0;
                w_r <= 0;
                //-----------------------------
            end

            DECODE : begin //#1
                state = EXECUTE; //#2
                if (instruction[19:18] == 2'b1) begin //std_op
                    operand1 <= regfile[instruction[15:14]]; //X2
                    operand2 <= regfile[instruction[13:12]]; //X3
                    offset <= instruction[11:4];
                    opcode <= instruction[3:0];
                    sel1 <= 1;
                    sel3 <= 0;
                    w_r <= 0;
                end else if (instruction[19:18] == 2'b10) begin //loadR 
                    operand1 <= regfile[instruction[15:14]]; //X2
                    operand2 <= regfile[instruction[17:16]]; //z
                    offset <= instruction[11:4];
                    opcode <= instruction[3:0];
                    sel1 <= 0; //pass data_out
                    sel3 <= 1; //pass offset
                    w_r <= 0;
                end else if (instruction[19:18] == 2'b11) begin //storeR
                    operand1 <= regfile[instruction[15:14]]; //X2
                    operand2 <= regfile[instruction[17:16]]; //z
                    offset <= instruction[11:4];
                    opcode <= instruction[3:0];
                    sel1 <= 0;
                    sel3 <= 1; //pass offset
                    w_r <= 0;
                end
            end
            EXECUTE: begin //#2
                state = MEM_ACCESS; //#3
                if (instruction[19:18] == 2'b01) begin //std_op
                    state = WRITE_BACK;
                    operand1 <= regfile[instruction[15:14]]; //X2
                    operand2 <= regfile[instruction[13:12]]; //X3
                    offset <= instruction[11:4];
                    opcode <= instruction[3:0];
                    sel1 <= 1;
                    sel3 <= 0;
                    w_r <= 0;

                end else if (instruction[19:18] == 2'b10) begin //loadR  
                    operand1 <= regfile[instruction[15:14]]; //X2
                    operand2 <= regfile[instruction[17:16]]; //z
                    offset <= instruction[11:4];
                    opcode <= instruction[3:0];
                    sel1 <= 0; //pass data_out
                    sel3 <= 1; //pass offset
                    w_r <= 0;
                end else if (instruction[19:18] == 2'b11) begin //storeR
                    operand1 <= regfile[instruction[15:14]]; //X2
                    operand2 <= regfile[instruction[17:16]]; //z
                    offset <= instruction[11:4];
                    opcode <= instruction[3:0];
                    sel1 <= 0;
                    sel3 <= 1; //pass offset
                    w_r <= 1;
                end
            end
            MEM_ACCESS: begin //#3
                state = WRITE_BACK; //#4
                if (instruction[19:18] == 2'b10) begin //loadR             
                    operand1 <= regfile[instruction[15:14]]; //X2
                    operand2 <= regfile[instruction[17:16]]; //z
                    offset <= instruction[11:4];
                    opcode <= instruction[3:0];
                    sel1 <= 0; //pass data_out
                    sel3 <= 1; //pass offset
                    w_r <= 0;
                end else if (instruction[19:18] == 2'b11) begin //storeR 
                    state = DECODE; 
                    
                    operand1 <= regfile[instruction[15:14]]; //X2
                    operand2 <= regfile[instruction[17:16]]; //z
                    offset <= instruction[11:4];
                    opcode <= instruction[3:0];
                    sel1 <= 0;
                    sel3 <= 1; //pass offset
                    w_r <= 1;  //enable write_enable
                end
            end
            WRITE_BACK: begin //#4
                state = DECODE; //#1
                if (instruction[19:18] == 2'b01) begin //std_op
                    regfile[instruction[17:16]] <= result2; //X1

                    operand1 <= regfile[instruction[15:14]]; //X2
                    operand2 <= regfile[instruction[13:12]]; //X3
                    offset <= instruction[11:4];
                    opcode <= instruction[3:0];
                    sel1 <= 1;
                    sel3 <= 0;
                    w_r <= 0;
                end else if (instruction[19:18] == 2'b11) begin //storeR
                   
                    operand1 <= regfile[instruction[15:14]]; //X2
                    operand2 <= regfile[instruction[17:16]]; //z
                    offset <= instruction[11:4];
                    opcode <= instruction[3:0];
                    sel1 <= 0; //pass data_out
                    sel3 <= 1; //pass offset
                    w_r <= 0; //disable write_enable again
                end
                else if (instruction[19:18] == 2'b10) begin //loadR
                    regfile[instruction[17:16]] <= result2; //From data mem
                    operand1 <= regfile[instruction[15:14]]; //X2
                    operand2 <= regfile[instruction[17:16]]; //z
                    offset <= instruction[11:4];
                    opcode <= instruction[3:0];
                    sel1 <= 0; //pass data_out
                    sel3 <= 1; //pass offset
                    w_r <= 0;
                end
            end

            default: // Fault Recovery
            state = RESET; //#0
        endcase
    end
endmodule

module alu( clk, operand_a, operand_b, opcode, result);
    parameter DATA_WIDTH = 8;

    input clk;
    input[DATA_WIDTH-1:0]operand_a,operand_b;
    input [3:0] opcode;
    output reg[DATA_WIDTH-1:0] result;
    
  always@(posedge clk)
    begin
     case(opcode)
        4'b0000: //Addition
           result <= operand_a + operand_b ; 
        4'b0001: //Subtraction 
           result <= operand_a - operand_b;
        default: result <= 8'bx; 
     endcase
     
    end
endmodule

`timescale 1ns / 1ps

module simple_cpu( clk, rst, instruction );

    parameter DATA_WIDTH = 8; //8 bit wide data
    parameter ADDR_BITS = 5; //32 Addresses
    parameter INSTR_WIDTH =20; //20b instruction

    input [INSTR_WIDTH-1:0] instruction;
    input clk, rst;

    //Wires for connecting to data memory    
    wire [ADDR_BITS-1:0] addr_i;
    wire [DATA_WIDTH-1:0] data_in_i, data_out_i, result2_i ;
    wire wen_i; 
    wire [DATA_WIDTH-1:0] r0, r1, r2, r3;
    
    //wire for connecting to the ALU
    wire [DATA_WIDTH-1:0]operand_a_i, operand_b_i, result1_i;
    wire [3:0]opcode_i;
    
   
    //Wire for connecting to CU
    wire [DATA_WIDTH-1:0]offset_i;
    wire sel1_i, sel3_i;
    wire [DATA_WIDTH-1:0] operand_1_i, operand_2_i;
    
    //Instantiating an alu1
    alu #(DATA_WIDTH) alu1 (clk, operand_a_i, operand_b_i, opcode_i, result1_i);
     
    //instantiation of data memory
  reg_mem  #(DATA_WIDTH,ADDR_BITS) data_memory(result1_i, data_in_i, wen_i, clk, data_out_i);
    
    //Instantiation of a CU, now with correct parameters for EPWave
    CU  #(DATA_WIDTH,ADDR_BITS, INSTR_WIDTH) CU1(clk, rst, instruction, result2_i,
        operand_1_i, operand_2_i, offset_i, opcode_i, sel1_i, sel3_i, wen_i, r0, r1, r2, r3);
    

    
    //Connect CU to ALU
    assign operand_a_i = operand_1_i;
    assign operand_b_i = (sel3_i == 0) ? operand_2_i: (sel3_i == 1) ? offset_i : 8'bx;
    
    //Connect CU to Memory
    assign data_in_i = operand_2_i;
    
    //Connect datamem to CU
    assign result2_i = (sel1_i == 0) ? data_out_i : (sel1_i == 1) ? result1_i : 8'bx;  
  

endmodule

Prac6/testbench with LOADR extension.sv
`timescale 1ns / 1ps
module tb_simple_CPU;
       
    parameter DATA_WIDTH = 8; //8 bit wide data
    parameter ADDR_BITS = 5; //32 Addresses
    parameter INSTR_WIDTH =20; //20b instruction
   
    reg clk, rst;
    reg [INSTR_WIDTH-1:0] instruction;

    
    simple_cpu  #(DATA_WIDTH,ADDR_BITS,INSTR_WIDTH) SCPU_DUT(clk, rst, instruction);
    	
    initial begin
      //start recording epWave
        $dumpfile("dump.vcd");
        $dumpvars();
      //monitor variables in console
      $monitor("%d   %d   %d   %d", SCPU_DUT.CU1.regfile[0], SCPU_DUT.CU1.regfile[1], SCPU_DUT.CU1.regfile[2], SCPU_DUT.CU1.regfile[3]);
        clk = 1'b0;
        rst = 1'b1;
        instruction = 20'd0;
      repeat(2) #1 clk=!clk;
        rst = 1'b0;
        repeat(2) #1 clk=!clk;
                
                
        /*Info on the simple CPU:
            * Reset sets regfile = [0,1,2,3]
            * ADD = opcode 0, SUB = opcode 1  
        */
            
                                        //ADD:    reg0  = reg1 + reg3   //1+3=4
        //In the instruction this is:    (instr)  (X1)    (X2)   (X3)  
        instruction = 20'b01000111000000000000;
      repeat(8) #1 clk=!clk; //4 rising edges
        
                                        //ADD:    reg1  = reg0 + reg3   //4+3=7
        //In the instruction this is:    (instr)  (X1)    (X2)   (X3)
        instruction = 20'b01010011000000000000;
      repeat(6) #1 clk=!clk; 
                
                                         //SUB:   reg3  = reg0 - reg2  //4-2=2  
       //In the instruction this is:    (instr)  (X1)    (X2)   (X3) 
        instruction = 20'b01110010000000000001;
      repeat(6) #1 clk=!clk;
        
                                         //STORE_R:   DATA_MEM(reg2 + 15) = reg1  //DATA_MEM(2+15)=7  
        //In the instruction this is:    (instr)               (X2)         (X1)
        instruction = 20'b11011000000011110000;
      repeat(6) #1 clk=!clk;
        
                                           //STORE_R:   DATA_MEM(reg3 + 22) = reg0  //DATA_MEM(2+22)= 4  
        //In the instruction this is:    (instr)                 (X2)         (X1)
        instruction = 20'b11001100000101100000;
      repeat(6) #1 clk=!clk;

                                           //LOAD_R:   DATA_MEM(reg2 + 15) = reg3  //reg3 = DATA_MEM(2+15)  -> reg3 becomes 7  
        //In the instruction this is:    (instr)                (X2)         (X1)
        instruction = 20'b10111000000011110000;
      repeat(8) #1 clk=!clk;


      //Additional LOAD_r: DATA_MEM(reg0 + 20) = reg3
      instruction = 20'b10110000000101000000;
      repeat(8) #1 clk=!clk;
    end 
    
endmodule

Prac6/dump.vcd
$date
	Wed Nov  3 17:25:08 2021
$end
$version
	Icarus Verilog
$end
$timescale
	1ps
$end
$scope module tb_simple_CPU $end
$var reg 1 ! clk $end
$var reg 20 " instruction [19:0] $end
$var reg 1 # rst $end
$scope module SCPU_DUT $end
$var wire 1 ! clk $end
$var wire 8 $ data_in_i [7:0] $end
$var wire 20 % instruction [19:0] $end
$var wire 8 & operand_a_i [7:0] $end
$var wire 1 # rst $end
$var wire 1 ' wen_i $end
$var wire 1 ( sel3_i $end
$var wire 1 ) sel1_i $end
$var wire 8 * result2_i [7:0] $end
$var wire 8 + result1_i [7:0] $end
$var wire 8 , r3 [7:0] $end
$var wire 8 - r2 [7:0] $end
$var wire 8 . r1 [7:0] $end
$var wire 8 / r0 [7:0] $end
$var wire 8 0 operand_b_i [7:0] $end
$var wire 8 1 operand_2_i [7:0] $end
$var wire 8 2 operand_1_i [7:0] $end
$var wire 4 3 opcode_i [3:0] $end
$var wire 8 4 offset_i [7:0] $end
$var wire 8 5 data_out_i [7:0] $end
$scope module CU1 $end
$var wire 1 ! clk $end
$var wire 20 6 instr [19:0] $end
$var wire 8 7 r0 [7:0] $end
$var wire 8 8 r1 [7:0] $end
$var wire 8 9 r2 [7:0] $end
$var wire 8 : r3 [7:0] $end
$var wire 8 ; result2 [7:0] $end
$var wire 1 # rst $end
$var reg 20 < instruction [19:0] $end
$var reg 8 = offset [7:0] $end
$var reg 4 > opcode [3:0] $end
$var reg 8 ? operand1 [7:0] $end
$var reg 8 @ operand2 [7:0] $end
$var reg 1 ) sel1 $end
$var reg 1 ( sel3 $end
$var reg 4 A state [3:0] $end
$var reg 1 ' w_r $end
$upscope $end
$scope module alu1 $end
$var wire 1 ! clk $end
$var wire 4 B opcode [3:0] $end
$var wire 8 C operand_a [7:0] $end
$var wire 8 D operand_b [7:0] $end
$var reg 8 E result [7:0] $end
$upscope $end
$scope module data_memory $end
$var wire 5 F addr [4:0] $end
$var wire 1 ! clk $end
$var wire 8 G data_in [7:0] $end
$var wire 1 ' wen $end
$var reg 8 H data_out [7:0] $end
$upscope $end
$upscope $end
$upscope $end
$enddefinitions $end
#0
$dumpvars
bx H
bx G
bx F
bx E
bx D
bx C
bx B
b0 A
bx @
bx ?
bx >
bx =
bx <
bx ;
bx :
bx 9
bx 8
bx 7
b0 6
bx 5
bx 4
bx 3
bx 2
bx 1
bx 0
bx /
bx .
bx -
bx ,
bx +
bx *
x)
x(
x'
bx &
b0 %
bx $
1#
b0 "
0!
$end
#1000
0'
0(
0)
b1111 3
b1111 >
b1111 B
b11 ,
b11 :
b10 -
b10 9
b1 .
b1 8
b0 /
b0 7
b0 <
1!
#2000
0#
0!
#3000
1!
#4000
b1000111000000000000 "
b1000111000000000000 %
b1000111000000000000 6
0!
#5000
b1 A
b1000111000000000000 <
1!
#6000
0!
#7000
b11 0
b11 D
1)
b0 3
b0 >
b0 B
b0 4
b0 =
b11 $
b11 G
b11 1
b11 @
b1 &
b1 C
b1 2
b1 ?
b10 A
1!
#8000
0!
#9000
b100 *
b100 ;
b100 F
b100 +
b100 E
b11 $
b11 G
b11 1
b11 @
b1 &
b1 C
b1 2
b1 ?
b1000 A
1!
#10000
0!
#11000
b100 /
b100 7
b11 $
b11 G
b11 1
b11 @
b1 &
b1 C
b1 2
b1 ?
b1 A
1!
#12000
b1010011000000000000 "
b1010011000000000000 %
b1010011000000000000 6
0!
#13000
b11 $
b11 G
b11 1
b11 @
b100 &
b100 C
b100 2
b100 ?
b10 A
b1010011000000000000 <
1!
#14000
0!
#15000
b111 *
b111 ;
b111 F
b111 +
b111 E
b1000 A
1!
#16000
0!
#17000
b111 .
b111 8
b1 A
1!
#18000
b1110010000000000001 "
b1110010000000000001 %
b1110010000000000001 6
0!
#19000
b10 0
b10 D
b1 3
b1 >
b1 B
b10 $
b10 G
b10 1
b10 @
b10 A
b1110010000000000001 <
1!
#20000
0!
#21000
b10 *
b10 ;
b10 F
b10 +
b10 E
b1000 A
1!
#22000
0!
#23000
b10 ,
b10 :
b1 A
1!
#24000
b11011000000011110000 "
b11011000000011110000 %
b11011000000011110000 6
0!
#25000
bx *
bx ;
b1111 0
b1111 D
1(
0)
b0 3
b0 >
b0 B
b1111 4
b1111 =
b111 $
b111 G
b111 1
b111 @
b10 &
b10 C
b10 2
b10 ?
b10 A
b11011000000011110000 <
1!
#26000
0!
#27000
b10001 F
1'
b10001 +
b10001 E
b100 A
1!
#28000
0!
#29000
b1 A
1!
#30000
b11001100000101100000 "
b11001100000101100000 %
b11001100000101100000 6
0!
#31000
b10110 0
b10110 D
0'
b10110 4
b10110 =
b100 $
b100 G
b100 1
b100 @
b10 A
b11001100000101100000 <
1!
#32000
0!
#33000
b11000 F
b111 *
b111 ;
b11000 +
b11000 E
b111 5
b111 H
1'
b100 A
1!
#34000
0!
#35000
b1 A
1!
#36000
b10111000000011110000 "
b10111000000011110000 %
b10111000000011110000 6
0!
#37000
b1111 0
b1111 D
b0 *
b0 ;
0'
b1111 4
b1111 =
b10 $
b10 G
b10 1
b10 @
b0 5
b0 H
b10 A
b10111000000011110000 <
1!
#38000
0!
#39000
b100 *
b100 ;
b10001 F
b100 5
b100 H
b10001 +
b10001 E
b100 A
1!
#40000
0!
#41000
b111 *
b111 ;
b111 5
b111 H
b1000 A
1!
#42000
0!
#43000
b111 ,
b111 :
b111 5
b111 H
b1 A
1!
#44000
b10110000000101000000 "
b10110000000101000000 %
b10110000000101000000 6
0!
#45000
b10100 0
b10100 D
b10100 4
b10100 =
b111 $
b111 G
b111 1
b111 @
b100 &
b100 C
b100 2
b100 ?
b111 5
b111 H
b10 A
b10110000000101000000 <
1!
#46000
0!
#47000
b11000 F
b11000 +
b11000 E
b100 A
1!
#48000
0!
#49000
b100 *
b100 ;
b100 5
b100 H
b1000 A
1!
#50000
0!
#51000
b100 ,
b100 :
b1 A
1!
